rfidtools/RFID_Icon.ico
rfidtools/__init__.py
rfidtools/__main__.py
rfidtools/config_template.yaml
rfidtools/core.py
rfidtools/labels/__init__.py
rfidtools/labels/add.py
rfidtools/labels/print.py
rfidtools/labels/utils.py
rfidtools-2.0.1.dist-info/METADATA
rfidtools-2.0.1.dist-info/WHEEL
rfidtools-2.0.1.dist-info/RECORD
